intensio_obfuscator/__init__.py
intensio_obfuscator/intensio_obfuscator.py
intensio_obfuscator/core/obfuscation/__init__.py
intensio_obfuscator/core/obfuscation/intensio_analyze.py
intensio_obfuscator/core/obfuscation/intensio_delete.py
intensio_obfuscator/core/obfuscation/intensio_mixer.py
intensio_obfuscator/core/obfuscation/intensio_padding.py
intensio_obfuscator/core/obfuscation/intensio_replace.py
intensio_obfuscator/core/utils/__init__.py
intensio_obfuscator/core/utils/intensio_design.py
intensio_obfuscator/core/utils/intensio_exclude.py
intensio_obfuscator/core/utils/intensio_usage.py
intensio_obfuscator/core/utils/intensio_utils.py
intensio_obfuscator/exclude_examples/exclude_files_name_by_user.txt
intensio_obfuscator/exclude_examples/exclude_words_by_user.txt
intensio_obfuscator/obfuscation_examples/python/advanced/input/basicRAT-example/README.md
intensio_obfuscator/obfuscation_examples/python/advanced/input/basicRAT-example/UNLICENSE
intensio_obfuscator/obfuscation_examples/python/advanced/input/basicRAT-example/basicRAT_client.py
intensio_obfuscator/obfuscation_examples/python/advanced/input/basicRAT-example/basicRAT_server.py
intensio_obfuscator/obfuscation_examples/python/advanced/input/basicRAT-example/core/__init__.py
intensio_obfuscator/obfuscation_examples/python/advanced/input/basicRAT-example/core/common.py
intensio_obfuscator/obfuscation_examples/python/advanced/input/basicRAT-example/core/crypto.py
intensio_obfuscator/obfuscation_examples/python/advanced/input/basicRAT-example/core/filesock.py
intensio_obfuscator/obfuscation_examples/python/advanced/input/basicRAT-example/core/persistence.py
intensio_obfuscator/obfuscation_examples/python/advanced/input/basicRAT-example/core/scan.py
intensio_obfuscator/obfuscation_examples/python/advanced/input/basicRAT-example/core/survey.py
intensio_obfuscator/obfuscation_examples/python/advanced/input/basicRAT-example/core/toolkit.py
intensio_obfuscator-1.0.10.6.dist-info/LICENSE.txt
intensio_obfuscator-1.0.10.6.dist-info/METADATA
intensio_obfuscator-1.0.10.6.dist-info/WHEEL
intensio_obfuscator-1.0.10.6.dist-info/entry_points.txt
intensio_obfuscator-1.0.10.6.dist-info/top_level.txt
intensio_obfuscator-1.0.10.6.dist-info/RECORD
