Metadata-Version: 2.1
Name: intensio-obfuscator
Version: 1.0.10.6
Summary: Obfuscate a python code 2.x and 3.x 
Home-page: https://github.com/Hnfull/Intensio-Obfuscator
Author: hnfull
Author-email: gitland@protonmail.com
License: MIT
Keywords: python
Platform: UNKNOWN
Classifier: Programming Language :: Python :: 3
Classifier: License :: OSI Approved :: MIT License
Classifier: Operating System :: OS Independent
Requires-Python: >=3.5
Requires-Dist: progress (>=1.5)
